{
  "title": "血糖値を整えると、日中のだるさが減る",
  "media": "stand.fm",
  "date": "2026-06-20",
  "tags": [
    "睡眠",
    "身体",
    "食事"
  ],
  "url": "https://stand.fm/episodes/6a311e423fcbe7e0b3fd5f52",
  "description": "血糖値の安定が、日中のだるさや眠気、夜の休みやすさに関わると感じた回。",
  "detail": " 血糖値の乱高下は、夜の睡眠だけでなく、日中の集中力、眠気、気分にも影響する。 食後に急に眠くなる時は、**意志力の問題ではなく、体のエネルギーの波が大きくなっている可能性がある**。 やったことは、糖質を最初に食べるのではなく、先にタンパク質を入れること。 **食べる順番を変えるだけ**でも、血糖値の急上昇と急降下がゆるやかになり、だるさが出にくくなる。 特に昼食後に眠気が強い人ほど、まずここから試しやすい。 制限ではなく、同じ食事の中で順番を変えるだけなので、続けるハードルが低い。"
}
